psicollect/__init__.py
psicollect/cataloging/__init__.py
psicollect/cataloging/catalog.py
psicollect/cataloging/make_catalog.py
psicollect/cataloging/stack.py
psicollect/collector/__init__.py
psicollect/collector/archive.py
psicollect/collector/collect.py
psicollect/collector/connection_handler.py
psicollect/collector/locking.py
psicollect/collector/response_getter.py
psicollect/collector/storm.py
psicollect/common/__init__.py
psicollect/common/h.py
psicollect/common/pstorm.py
psicollect/common/s.py
psi_collect-1.0.1.dist-info/LICENSE
psi_collect-1.0.1.dist-info/METADATA
psi_collect-1.0.1.dist-info/WHEEL
psi_collect-1.0.1.dist-info/entry_points.txt
psi_collect-1.0.1.dist-info/top_level.txt
psi_collect-1.0.1.dist-info/RECORD
