Metadata-Version: 2.1
Name: psi-collect
Version: 1.0.1
Summary: Collection, aggregation, and cataloging of NOAA post-storm emergency response imagery.
Home-page: https://github.com/UNCG-DAISY/psi-collect/
Author: PSI Team
License: MIT license
Project-URL: Documentation, https://psi-collect.readthedocs.io/en/latest/
Project-URL: Source, https://github.com/UNCG-DAISY/psi-collect/
Project-URL: Tracker, https://github.com/UNCG-DAISY/psi-collect/issues
Keywords: python
Platform: UNKNOWN
Classifier: Development Status :: 5 - Production/Stable
Classifier: Environment :: Console
Classifier: Intended Audience :: Developers
Classifier: Intended Audience :: Education
Classifier: Intended Audience :: Science/Research
Classifier: License :: OSI Approved :: MIT License
Classifier: Natural Language :: English
Classifier: Programming Language :: Python :: 3
Classifier: Programming Language :: Python :: 3.6
Classifier: Programming Language :: Python :: 3.7
Classifier: Programming Language :: Python :: 3.8
Classifier: Topic :: Scientific/Engineering
Classifier: Topic :: Scientific/Engineering :: Atmospheric Science
Requires-Python: >=3.6
Requires-Dist: requests
Requires-Dist: tqdm
Requires-Dist: pandas
Requires-Dist: Pillow
Requires-Dist: imageio
